glasscandle/__about__.py
glasscandle/__init__.py
glasscandle/__main__.py
glasscandle/db.py
glasscandle/http.py
glasscandle/parsers.py
glasscandle/pool.py
glasscandle/version_constraints.py
glasscandle/watcher.py
glasscandle/notifications/__init__.py
glasscandle/notifications/bsky.py
glasscandle/notifications/email.py
glasscandle/notifications/mastodon.py
glasscandle/notifications/slack.py
glasscandle/providers/__init__.py
glasscandle/providers/base.py
glasscandle/providers/bioconda.py
glasscandle/providers/conda.py
glasscandle/providers/condaforge.py
glasscandle/providers/pypi.py
glasscandle/providers/url.py
glasscandle-0.1.1.dist-info/METADATA
glasscandle-0.1.1.dist-info/WHEEL
glasscandle-0.1.1.dist-info/licenses/LICENSE.txt
glasscandle-0.1.1.dist-info/RECORD
