Metadata-Version: 2.4
Name: glasscandle
Version: 0.1.1
Project-URL: Documentation, https://github.com/wytamma/glasscandle#readme
Project-URL: Issues, https://github.com/wytamma/glasscandle/issues
Project-URL: Source, https://github.com/wytamma/glasscandle
Author-email: Wytamma Wirth <wytamma.wirth@me.com>
License-Expression: MIT
License-File: LICENSE.txt
Classifier: Development Status :: 4 - Beta
Classifier: Programming Language :: Python
Classifier: Programming Language :: Python :: 3.8
Classifier: Programming Language :: Python :: 3.9
Classifier: Programming Language :: Python :: 3.10
Classifier: Programming Language :: Python :: 3.11
Classifier: Programming Language :: Python :: 3.12
Classifier: Programming Language :: Python :: Implementation :: CPython
Classifier: Programming Language :: Python :: Implementation :: PyPy
Requires-Python: >=3.8
Requires-Dist: beautifulsoup4
Requires-Dist: click
Requires-Dist: mastodon-py
Requires-Dist: packaging
Requires-Dist: requests
